ttpassgen/__init__.py
ttpassgen/ttpassgen.py
ttpassgen-1.1.3.dist-info/LICENSE
ttpassgen-1.1.3.dist-info/METADATA
ttpassgen-1.1.3.dist-info/WHEEL
ttpassgen-1.1.3.dist-info/entry_points.txt
ttpassgen-1.1.3.dist-info/top_level.txt
ttpassgen-1.1.3.dist-info/RECORD
