Metadata-Version: 2.1
Name: ttpassgen
Version: 1.1.3
Summary: A highly flexiable and scriptable password dictionary generator.
Home-page: https://github.com/tp7309/TTPassGen
Author: tp7309
Author-email: yiyou7309@gmail.com
License: Apache License Version 2.0
Keywords: ttpassgen crunch password-generator wordlist password-dict password-dict-generator brute-force word-combination
Classifier: Programming Language :: Python :: 3
License-File: LICENSE
Requires-Dist: click
Requires-Dist: tqdm
